{
  "generated_at": "2026-02-23T14:57:33+00:00",
  "strict": true,
  "heartbeat_path": "docs/etl/runs/citizen_concern_pack_outcomes_heartbeat.jsonl",
  "window_last": 20,
  "thresholds": {
    "max_failed": 0,
    "max_failed_rate_pct": 0.0,
    "max_degraded": 0,
    "max_degraded_rate_pct": 0.0,
    "max_contract_incomplete": 0,
    "max_contract_incomplete_rate_pct": 0.0,
    "max_weak_pack_followthrough_violations": 0,
    "max_weak_pack_followthrough_violation_rate_pct": 0.0,
    "max_unknown_pack_select_share_violations": 0,
    "max_unknown_pack_select_share_violation_rate_pct": 0.0
  },
  "entries_total": 1,
  "entries_in_window": 1,
  "malformed_entries_in_window": 0,
  "status_counts": {
    "ok": 1,
    "degraded": 0,
    "failed": 0
  },
  "failed_in_window": 0,
  "failed_rate_pct": 0.0,
  "degraded_in_window": 0,
  "degraded_rate_pct": 0.0,
  "contract_incomplete_in_window": 0,
  "contract_incomplete_rate_pct": 0.0,
  "weak_pack_followthrough_violations_in_window": 0,
  "weak_pack_followthrough_violation_rate_pct": 0.0,
  "unknown_pack_select_share_violations_in_window": 0,
  "unknown_pack_select_share_violation_rate_pct": 0.0,
  "first_failed_run_at": "",
  "last_failed_run_at": "",
  "first_degraded_run_at": "",
  "last_degraded_run_at": "",
  "first_contract_incomplete_run_at": "",
  "last_contract_incomplete_run_at": "",
  "latest": {
    "run_at": "2026-02-23T12:25:20+00:00",
    "heartbeat_id": "2026-02-23T12:25:20+00:00|ok|2026-02-23T12:25:20+00:00|24|7|7|1.000000|0.083333|20|5|0.300000|0.200000|1||",
    "status": "ok",
    "line_no": 1,
    "malformed_line": false,
    "digest_generated_at": "2026-02-23T12:25:20+00:00",
    "weak_pack_followthrough_rate": 1.0,
    "unknown_pack_select_share": 0.083333,
    "contract_complete": true,
    "weak_pack_followthrough_rate_meets_minimum": true,
    "unknown_pack_select_share_within_threshold": true
  },
  "failed_streak_latest": 0,
  "degraded_streak_latest": 0,
  "checks": {
    "window_nonempty_ok": true,
    "malformed_entries_ok": true,
    "max_failed_ok": true,
    "max_failed_rate_ok": true,
    "max_degraded_ok": true,
    "max_degraded_rate_ok": true,
    "max_contract_incomplete_ok": true,
    "max_contract_incomplete_rate_ok": true,
    "max_weak_pack_followthrough_violations_ok": true,
    "max_weak_pack_followthrough_violation_rate_ok": true,
    "max_unknown_pack_select_share_violations_ok": true,
    "max_unknown_pack_select_share_violation_rate_ok": true,
    "latest_not_failed_ok": true,
    "latest_contract_complete_ok": true,
    "latest_thresholds_ok": true
  },
  "strict_fail_reasons": [],
  "status": "ok"
}
