{
  "data": [
    {
      "convocatoria_id": "AUTO-AND-2026-2001",
      "concesion_id": "AUTO-AND-2026-3001",
      "organo_concedente": "Junta de Andalucia",
      "beneficiario": "Fundacion Innova Sur",
      "nif": "G11223344",
      "cuantia": "75000,00",
      "fecha_publicacion": "2026-02-14",
      "url": "https://www.pap.hacienda.gob.es/bdnstrans/GE/es/autonomico/andalucia/3001",
      "comunidadAutonoma": "AN"
    },
    {
      "convocatoria_id": "AUTO-CAT-2026-2002",
      "organo_concedente": "Generalitat de Catalunya",
      "beneficiarioNombre": "Centre Tecnologic Delta",
      "importe_eur": 52100,
      "fecha": "2026-02-13",
      "url": "https://www.pap.hacienda.gob.es/bdnstrans/GE/es/autonomico/catalunya/3002",
      "ccaa": "CT"
    }
  ]
}
