{"list_url": "https://www.jgpa.es/diputados-y-diputadas?p_p_id=jgpaportlet_WAR_jgpaportlet_INSTANCE_JoGQRoxbw79k&p_p_lifecycle=0&p_p_state=normal&p_p_mode=view&p_p_col_id=column-2&p_p_col_count=1&p_r_p_2113237475_diputadoId=0&p_r_p_2113237475_legislaturaId=0&p_r_p_2113237475_grupoParlamentarioId=0&_jgpaportlet_WAR_jgpaportlet_INSTANCE_JoGQRoxbw79k_redirect=%2Fdiputados-y-diputadas&_jgpaportlet_WAR_jgpaportlet_INSTANCE_JoGQRoxbw79k_delta=50&_jgpaportlet_WAR_jgpaportlet_INSTANCE_JoGQRoxbw79k_keywords=&_jgpaportlet_WAR_jgpaportlet_INSTANCE_JoGQRoxbw79k_advancedSearch=false&_jgpaportlet_WAR_jgpaportlet_INSTANCE_JoGQRoxbw79k_andOperator=true&_jgpaportlet_WAR_jgpaportlet_INSTANCE_JoGQRoxbw79k_resetCur=false&cur=1", "records": [{"diputado_id": "31306", "full_name": "Alonso Alonso, Rafael", "group_name": "Grupo Parlamentario Popular", "seat_number": null, "source_record_id": "id:31306"}, {"diputado_id": "31557", "full_name": "\u00c1lvarez N\u00fa\u00f1ez, Alba", "group_name": "Grupo Parlamentario Socialista", "seat_number": null, "source_record_id": "id:31557"}, {"diputado_id": "31448", "full_name": "\u00c1lvarez Rouco, Sara Concepci\u00f3n", "group_name": "Grupo Parlamentario Vox", "seat_number": null, "source_record_id": "id:31448"}, {"diputado_id": "31642", "full_name": "Barb\u00f3n Rodr\u00edguez, Adri\u00e1n", "group_name": "Grupo Parlamentario Socialista", "seat_number": null, "source_record_id": "id:31642"}, {"diputado_id": "31454", "full_name": "Bra\u00f1a Santos, Jacinto", "group_name": "Grupo Parlamentario Socialista", "seat_number": null, "source_record_id": "id:31454"}, {"diputado_id": "31325", "full_name": "Camino Rodr\u00edguez, Sandra Mar\u00eda", "group_name": "Grupo Parlamentario Popular", "seat_number": null, "source_record_id": "id:31325"}, {"diputado_id": "31625", "full_name": "Campomanes Isidoro, Delia", "group_name": "Grupo Parlamentario Convocatoria por Asturies IU-M\u00e1s Pa\u00eds-IAS", "seat_number": null, "source_record_id": "id:31625"}, {"diputado_id": "31641", "full_name": "Carcedo Garc\u00eda, Mar\u00eda Dolores", "group_name": "Grupo Parlamentario Socialista", "seat_number": null, "source_record_id": "id:31641"}, {"diputado_id": "31499", "full_name": "Centeno Mart\u00edn, Gonzalo", "group_name": "Grupo Parlamentario Vox", "seat_number": null, "source_record_id": "id:31499"}, {"diputado_id": "31462", "full_name": "Cifuentes Corujo, Manuel", "group_name": "Grupo Parlamentario Popular", "seat_number": null, "source_record_id": "id:31462"}, {"diputado_id": "31394", "full_name": "Cofi\u00f1o Gonz\u00e1lez, Juan Manuel", "group_name": "Grupo Parlamentario Socialista", "seat_number": null, "source_record_id": "id:31394"}, {"diputado_id": "31323", "full_name": "Costillas Guti\u00e9rrez, Jos\u00e9 Luis", "group_name": "Grupo Parlamentario Popular", "seat_number": null, "source_record_id": "id:31323"}, {"diputado_id": "31308", "full_name": "Cuervas-Mons Garc\u00eda-Braga, Jos\u00e9 Agust\u00edn", "group_name": "Grupo Parlamentario Popular", "seat_number": null, "source_record_id": "id:31308"}, {"diputado_id": "31464", "full_name": "de Rueda Gallardo, Pedro", "group_name": "Grupo Parlamentario Popular", "seat_number": null, "source_record_id": "id:31464"}, {"diputado_id": "31452", "full_name": "Felgueres Abad, Jos\u00e9 Manuel", "group_name": "Grupo Parlamentario Popular", "seat_number": null, "source_record_id": "id:31452"}, {"diputado_id": "31546", "full_name": "Fern\u00e1ndez Arias, Susana", "group_name": "Grupo Parlamentario Popular", "seat_number": null, "source_record_id": "id:31546"}, {"diputado_id": "31534", "full_name": "Fern\u00e1ndez Fern\u00e1ndez, Mar\u00eda Celia", "group_name": "Grupo Parlamentario Socialista", "seat_number": null, "source_record_id": "id:31534"}, {"diputado_id": "31592", "full_name": "Fern\u00e1ndez Fern\u00e1ndez, Lidia", "group_name": "Grupo Parlamentario Socialista", "seat_number": null, "source_record_id": "id:31592"}, {"diputado_id": "31547", "full_name": "Fern\u00e1ndez Huerga, Luis Ram\u00f3n", "group_name": "Grupo Parlamentario Socialista", "seat_number": null, "source_record_id": "id:31547"}, {"diputado_id": "31550", "full_name": "Fern\u00e1ndez Pardo, Mar\u00eda del Pilar", "group_name": "Grupo Parlamentario Popular", "seat_number": null, "source_record_id": "id:31550"}, {"diputado_id": "31449", "full_name": "Fern\u00e1ndez Rodr\u00edguez, Ricardo", "group_name": "Grupo Parlamentario Socialista", "seat_number": null, "source_record_id": "id:31449"}, {"diputado_id": "31586", "full_name": "Freile Fern\u00e1ndez, Mar\u00eda Esther", "group_name": "Grupo Parlamentario Socialista", "seat_number": null, "source_record_id": "id:31586"}, {"diputado_id": "31497", "full_name": "Garc\u00eda Fern\u00e1ndez, Mar\u00eda Gloria", "group_name": "Grupo Parlamentario Popular", "seat_number": null, "source_record_id": "id:31497"}, {"diputado_id": "31466", "full_name": "Garc\u00eda Gonz\u00e1lez, Jos\u00e9 Ram\u00f3n", "group_name": "Grupo Parlamentario Socialista", "seat_number": null, "source_record_id": "id:31466"}, {"diputado_id": "31501", "full_name": "Gonz\u00e1lez Cachero, Ana Isabel", "group_name": "Grupo Parlamentario Socialista", "seat_number": null, "source_record_id": "id:31501"}, {"diputado_id": "31636", "full_name": "Gonz\u00e1lez-Nuevo V\u00e1zquez, Nuria", "group_name": "Grupo Parlamentario Popular", "seat_number": null, "source_record_id": "id:31636"}, {"diputado_id": "31595", "full_name": "Gonz\u00e1lez Vegas, Javier", "group_name": "Grupo Parlamentario Convocatoria por Asturies IU-M\u00e1s Pa\u00eds-IAS", "seat_number": null, "source_record_id": "id:31595"}, {"diputado_id": "31303", "full_name": "Jov\u00e9 Sandoval, Javier", "group_name": "Grupo Parlamentario Vox", "seat_number": null, "source_record_id": "id:31303"}, {"diputado_id": "31588", "full_name": "Llamedo Gonz\u00e1lez, Jimena", "group_name": "Grupo Parlamentario Socialista", "seat_number": null, "source_record_id": "id:31588"}, {"diputado_id": "31332", "full_name": "L\u00f3pez Fern\u00e1ndez, Carolina", "group_name": "Grupo Parlamentario Vox", "seat_number": null, "source_record_id": "id:31332"}, {"diputado_id": "31646", "full_name": "Mac\u00edas Mariano, Noelia", "group_name": "Grupo Parlamentario Socialista", "seat_number": null, "source_record_id": "id:31646"}, {"diputado_id": "31318", "full_name": "Marcos L\u00edndez, Marcelino", "group_name": "Grupo Parlamentario Socialista", "seat_number": null, "source_record_id": "id:31318"}, {"diputado_id": "31525", "full_name": "M\u00e9ndez M\u00e9ndez, Salvador", "group_name": "Grupo Parlamentario Popular", "seat_number": null, "source_record_id": "id:31525"}, {"diputado_id": "31621", "full_name": "Morales Fuentecilla, \u00c1ngel Ricardo", "group_name": "Grupo Parlamentario Socialista", "seat_number": null, "source_record_id": "id:31621"}, {"diputado_id": "31590", "full_name": "Polledo Enr\u00edquez, Beatriz", "group_name": "Grupo Parlamentario Popular", "seat_number": null, "source_record_id": "id:31590"}, {"diputado_id": "31457", "full_name": "Puerto Prado, Ana Isabel", "group_name": "Grupo Parlamentario Socialista", "seat_number": null, "source_record_id": "id:31457"}, {"diputado_id": "31576", "full_name": "Pumares Su\u00e1rez, Adri\u00e1n", "group_name": "Grupo Parlamentario Mixto", "seat_number": null, "source_record_id": "id:31576"}, {"diputado_id": "31558", "full_name": "Queipo Somoano, \u00c1lvaro", "group_name": "Grupo Parlamentario Popular", "seat_number": null, "source_record_id": "id:31558"}, {"diputado_id": "31572", "full_name": "Ronderos Garc\u00eda, M\u00f3nica", "group_name": "Grupo Parlamentario Socialista", "seat_number": null, "source_record_id": "id:31572"}, {"diputado_id": "31598", "full_name": "Ruiz Riestra, Andr\u00e9s David", "group_name": "Grupo Parlamentario Popular", "seat_number": null, "source_record_id": "id:31598"}, {"diputado_id": "31593", "full_name": "S\u00e1nchez Hern\u00e1ndez, Salom\u00e9", "group_name": "Grupo Parlamentario Popular", "seat_number": null, "source_record_id": "id:31593"}, {"diputado_id": "31327", "full_name": "Su\u00e1rez Fern\u00e1ndez, Ren\u00e9", "group_name": "Grupo Parlamentario Socialista", "seat_number": null, "source_record_id": "id:31327"}, {"diputado_id": "31583", "full_name": "Tom\u00e9 Nestal, Covadonga", "group_name": "Grupo Parlamentario Mixto", "seat_number": null, "source_record_id": "id:31583"}, {"diputado_id": "31622", "full_name": "Venta Cueli, Luis Miguel", "group_name": "Grupo Parlamentario Popular", "seat_number": null, "source_record_id": "id:31622"}, {"diputado_id": "31569", "full_name": "Zapico Gonz\u00e1lez, Ovidio", "group_name": "Grupo Parlamentario Convocatoria por Asturies IU-M\u00e1s Pa\u00eds-IAS", "seat_number": null, "source_record_id": "id:31569"}], "source": "jgpa_diputados_list"}